general_handler/general_handler.py
general_handler/manifest.toml
opsbox_general_handler-0.2.0.dist-info/LICENCE.txt
opsbox_general_handler-0.2.0.dist-info/METADATA
opsbox_general_handler-0.2.0.dist-info/WHEEL
opsbox_general_handler-0.2.0.dist-info/entry_points.txt
opsbox_general_handler-0.2.0.dist-info/top_level.txt
opsbox_general_handler-0.2.0.dist-info/RECORD
