Metadata-Version: 2.2
Name: opsbox-general-handler
Version: 0.2.0
Summary: General Handler for opsbox.
Requires-Python: ==3.11.*
License-File: LICENCE.txt
Requires-Dist: loguru>=0.7.2
Requires-Dist: pluggy>=1.5.0
Requires-Dist: opsbox>=0.2.0
